{
  "dataset": "ACDC",
  "schema_version": 1,
  "split_type": "patient",
  "split_level": "patient",
  "patient_id_rule": "prefix_before_first_underscore",
  "seed": 42,
  "train_ratio": 0.8,
  "train_fraction": 0.8,
  "source_data_dir": "preprocessed_data/ACDC",
  "created_at": "2026-05-11T05:39:11.930972+00:00",
  "n_patients": 100,
  "num_patients": 100,
  "n_volumes": 200,
  "num_volumes": 200,
  "train_patients": [
    "patient001",
    "patient002",
    "patient003",
    "patient006",
    "patient007",
    "patient008",
    "patient009",
    "patient010",
    "patient011",
    "patient013",
    "patient016",
    "patient017",
    "patient019",
    "patient020",
    "patient021",
    "patient022",
    "patient023",
    "patient024",
    "patient025",
    "patient026",
    "patient027",
    "patient031",
    "patient033",
    "patient034",
    "patient035",
    "patient037",
    "patient038",
    "patient039",
    "patient040",
    "patient041",
    "patient042",
    "patient043",
    "patient044",
    "patient045",
    "patient046",
    "patient047",
    "patient048",
    "patient049",
    "patient050",
    "patient051",
    "patient052",
    "patient053",
    "patient054",
    "patient056",
    "patient057",
    "patient058",
    "patient059",
    "patient060",
    "patient061",
    "patient062",
    "patient063",
    "patient064",
    "patient066",
    "patient067",
    "patient068",
    "patient069",
    "patient071",
    "patient072",
    "patient073",
    "patient074",
    "patient075",
    "patient077",
    "patient078",
    "patient079",
    "patient080",
    "patient081",
    "patient083",
    "patient084",
    "patient085",
    "patient086",
    "patient088",
    "patient090",
    "patient091",
    "patient092",
    "patient093",
    "patient094",
    "patient096",
    "patient097",
    "patient099",
    "patient100"
  ],
  "val_patients": [
    "patient004",
    "patient005",
    "patient012",
    "patient014",
    "patient015",
    "patient018",
    "patient028",
    "patient029",
    "patient030",
    "patient032",
    "patient036",
    "patient055",
    "patient065",
    "patient070",
    "patient076",
    "patient082",
    "patient087",
    "patient089",
    "patient095",
    "patient098"
  ],
  "train_volumes": [
    "patient001_ED",
    "patient001_ES",
    "patient002_ED",
    "patient002_ES",
    "patient003_ED",
    "patient003_ES",
    "patient006_ED",
    "patient006_ES",
    "patient007_ED",
    "patient007_ES",
    "patient008_ED",
    "patient008_ES",
    "patient009_ED",
    "patient009_ES",
    "patient010_ED",
    "patient010_ES",
    "patient011_ED",
    "patient011_ES",
    "patient013_ED",
    "patient013_ES",
    "patient016_ED",
    "patient016_ES",
    "patient017_ED",
    "patient017_ES",
    "patient019_ED",
    "patient019_ES",
    "patient020_ED",
    "patient020_ES",
    "patient021_ED",
    "patient021_ES",
    "patient022_ED",
    "patient022_ES",
    "patient023_ED",
    "patient023_ES",
    "patient024_ED",
    "patient024_ES",
    "patient025_ED",
    "patient025_ES",
    "patient026_ED",
    "patient026_ES",
    "patient027_ED",
    "patient027_ES",
    "patient031_ED",
    "patient031_ES",
    "patient033_ED",
    "patient033_ES",
    "patient034_ED",
    "patient034_ES",
    "patient035_ED",
    "patient035_ES",
    "patient037_ED",
    "patient037_ES",
    "patient038_ED",
    "patient038_ES",
    "patient039_ED",
    "patient039_ES",
    "patient040_ED",
    "patient040_ES",
    "patient041_ED",
    "patient041_ES",
    "patient042_ED",
    "patient042_ES",
    "patient043_ED",
    "patient043_ES",
    "patient044_ED",
    "patient044_ES",
    "patient045_ED",
    "patient045_ES",
    "patient046_ED",
    "patient046_ES",
    "patient047_ED",
    "patient047_ES",
    "patient048_ED",
    "patient048_ES",
    "patient049_ED",
    "patient049_ES",
    "patient050_ED",
    "patient050_ES",
    "patient051_ED",
    "patient051_ES",
    "patient052_ED",
    "patient052_ES",
    "patient053_ED",
    "patient053_ES",
    "patient054_ED",
    "patient054_ES",
    "patient056_ED",
    "patient056_ES",
    "patient057_ED",
    "patient057_ES",
    "patient058_ED",
    "patient058_ES",
    "patient059_ED",
    "patient059_ES",
    "patient060_ED",
    "patient060_ES",
    "patient061_ED",
    "patient061_ES",
    "patient062_ED",
    "patient062_ES",
    "patient063_ED",
    "patient063_ES",
    "patient064_ED",
    "patient064_ES",
    "patient066_ED",
    "patient066_ES",
    "patient067_ED",
    "patient067_ES",
    "patient068_ED",
    "patient068_ES",
    "patient069_ED",
    "patient069_ES",
    "patient071_ED",
    "patient071_ES",
    "patient072_ED",
    "patient072_ES",
    "patient073_ED",
    "patient073_ES",
    "patient074_ED",
    "patient074_ES",
    "patient075_ED",
    "patient075_ES",
    "patient077_ED",
    "patient077_ES",
    "patient078_ED",
    "patient078_ES",
    "patient079_ED",
    "patient079_ES",
    "patient080_ED",
    "patient080_ES",
    "patient081_ED",
    "patient081_ES",
    "patient083_ED",
    "patient083_ES",
    "patient084_ED",
    "patient084_ES",
    "patient085_ED",
    "patient085_ES",
    "patient086_ED",
    "patient086_ES",
    "patient088_ED",
    "patient088_ES",
    "patient090_ED",
    "patient090_ES",
    "patient091_ED",
    "patient091_ES",
    "patient092_ED",
    "patient092_ES",
    "patient093_ED",
    "patient093_ES",
    "patient094_ED",
    "patient094_ES",
    "patient096_ED",
    "patient096_ES",
    "patient097_ED",
    "patient097_ES",
    "patient099_ED",
    "patient099_ES",
    "patient100_ED",
    "patient100_ES"
  ],
  "val_volumes": [
    "patient004_ED",
    "patient004_ES",
    "patient005_ED",
    "patient005_ES",
    "patient012_ED",
    "patient012_ES",
    "patient014_ED",
    "patient014_ES",
    "patient015_ED",
    "patient015_ES",
    "patient018_ED",
    "patient018_ES",
    "patient028_ED",
    "patient028_ES",
    "patient029_ED",
    "patient029_ES",
    "patient030_ED",
    "patient030_ES",
    "patient032_ED",
    "patient032_ES",
    "patient036_ED",
    "patient036_ES",
    "patient055_ED",
    "patient055_ES",
    "patient065_ED",
    "patient065_ES",
    "patient070_ED",
    "patient070_ES",
    "patient076_ED",
    "patient076_ES",
    "patient082_ED",
    "patient082_ES",
    "patient087_ED",
    "patient087_ES",
    "patient089_ED",
    "patient089_ES",
    "patient095_ED",
    "patient095_ES",
    "patient098_ED",
    "patient098_ES"
  ],
  "splits": {
    "train": {
      "patients": [
        "patient001",
        "patient002",
        "patient003",
        "patient006",
        "patient007",
        "patient008",
        "patient009",
        "patient010",
        "patient011",
        "patient013",
        "patient016",
        "patient017",
        "patient019",
        "patient020",
        "patient021",
        "patient022",
        "patient023",
        "patient024",
        "patient025",
        "patient026",
        "patient027",
        "patient031",
        "patient033",
        "patient034",
        "patient035",
        "patient037",
        "patient038",
        "patient039",
        "patient040",
        "patient041",
        "patient042",
        "patient043",
        "patient044",
        "patient045",
        "patient046",
        "patient047",
        "patient048",
        "patient049",
        "patient050",
        "patient051",
        "patient052",
        "patient053",
        "patient054",
        "patient056",
        "patient057",
        "patient058",
        "patient059",
        "patient060",
        "patient061",
        "patient062",
        "patient063",
        "patient064",
        "patient066",
        "patient067",
        "patient068",
        "patient069",
        "patient071",
        "patient072",
        "patient073",
        "patient074",
        "patient075",
        "patient077",
        "patient078",
        "patient079",
        "patient080",
        "patient081",
        "patient083",
        "patient084",
        "patient085",
        "patient086",
        "patient088",
        "patient090",
        "patient091",
        "patient092",
        "patient093",
        "patient094",
        "patient096",
        "patient097",
        "patient099",
        "patient100"
      ],
      "volumes": [
        "patient001_ED",
        "patient001_ES",
        "patient002_ED",
        "patient002_ES",
        "patient003_ED",
        "patient003_ES",
        "patient006_ED",
        "patient006_ES",
        "patient007_ED",
        "patient007_ES",
        "patient008_ED",
        "patient008_ES",
        "patient009_ED",
        "patient009_ES",
        "patient010_ED",
        "patient010_ES",
        "patient011_ED",
        "patient011_ES",
        "patient013_ED",
        "patient013_ES",
        "patient016_ED",
        "patient016_ES",
        "patient017_ED",
        "patient017_ES",
        "patient019_ED",
        "patient019_ES",
        "patient020_ED",
        "patient020_ES",
        "patient021_ED",
        "patient021_ES",
        "patient022_ED",
        "patient022_ES",
        "patient023_ED",
        "patient023_ES",
        "patient024_ED",
        "patient024_ES",
        "patient025_ED",
        "patient025_ES",
        "patient026_ED",
        "patient026_ES",
        "patient027_ED",
        "patient027_ES",
        "patient031_ED",
        "patient031_ES",
        "patient033_ED",
        "patient033_ES",
        "patient034_ED",
        "patient034_ES",
        "patient035_ED",
        "patient035_ES",
        "patient037_ED",
        "patient037_ES",
        "patient038_ED",
        "patient038_ES",
        "patient039_ED",
        "patient039_ES",
        "patient040_ED",
        "patient040_ES",
        "patient041_ED",
        "patient041_ES",
        "patient042_ED",
        "patient042_ES",
        "patient043_ED",
        "patient043_ES",
        "patient044_ED",
        "patient044_ES",
        "patient045_ED",
        "patient045_ES",
        "patient046_ED",
        "patient046_ES",
        "patient047_ED",
        "patient047_ES",
        "patient048_ED",
        "patient048_ES",
        "patient049_ED",
        "patient049_ES",
        "patient050_ED",
        "patient050_ES",
        "patient051_ED",
        "patient051_ES",
        "patient052_ED",
        "patient052_ES",
        "patient053_ED",
        "patient053_ES",
        "patient054_ED",
        "patient054_ES",
        "patient056_ED",
        "patient056_ES",
        "patient057_ED",
        "patient057_ES",
        "patient058_ED",
        "patient058_ES",
        "patient059_ED",
        "patient059_ES",
        "patient060_ED",
        "patient060_ES",
        "patient061_ED",
        "patient061_ES",
        "patient062_ED",
        "patient062_ES",
        "patient063_ED",
        "patient063_ES",
        "patient064_ED",
        "patient064_ES",
        "patient066_ED",
        "patient066_ES",
        "patient067_ED",
        "patient067_ES",
        "patient068_ED",
        "patient068_ES",
        "patient069_ED",
        "patient069_ES",
        "patient071_ED",
        "patient071_ES",
        "patient072_ED",
        "patient072_ES",
        "patient073_ED",
        "patient073_ES",
        "patient074_ED",
        "patient074_ES",
        "patient075_ED",
        "patient075_ES",
        "patient077_ED",
        "patient077_ES",
        "patient078_ED",
        "patient078_ES",
        "patient079_ED",
        "patient079_ES",
        "patient080_ED",
        "patient080_ES",
        "patient081_ED",
        "patient081_ES",
        "patient083_ED",
        "patient083_ES",
        "patient084_ED",
        "patient084_ES",
        "patient085_ED",
        "patient085_ES",
        "patient086_ED",
        "patient086_ES",
        "patient088_ED",
        "patient088_ES",
        "patient090_ED",
        "patient090_ES",
        "patient091_ED",
        "patient091_ES",
        "patient092_ED",
        "patient092_ES",
        "patient093_ED",
        "patient093_ES",
        "patient094_ED",
        "patient094_ES",
        "patient096_ED",
        "patient096_ES",
        "patient097_ED",
        "patient097_ES",
        "patient099_ED",
        "patient099_ES",
        "patient100_ED",
        "patient100_ES"
      ]
    },
    "val": {
      "patients": [
        "patient004",
        "patient005",
        "patient012",
        "patient014",
        "patient015",
        "patient018",
        "patient028",
        "patient029",
        "patient030",
        "patient032",
        "patient036",
        "patient055",
        "patient065",
        "patient070",
        "patient076",
        "patient082",
        "patient087",
        "patient089",
        "patient095",
        "patient098"
      ],
      "volumes": [
        "patient004_ED",
        "patient004_ES",
        "patient005_ED",
        "patient005_ES",
        "patient012_ED",
        "patient012_ES",
        "patient014_ED",
        "patient014_ES",
        "patient015_ED",
        "patient015_ES",
        "patient018_ED",
        "patient018_ES",
        "patient028_ED",
        "patient028_ES",
        "patient029_ED",
        "patient029_ES",
        "patient030_ED",
        "patient030_ES",
        "patient032_ED",
        "patient032_ES",
        "patient036_ED",
        "patient036_ES",
        "patient055_ED",
        "patient055_ES",
        "patient065_ED",
        "patient065_ES",
        "patient070_ED",
        "patient070_ES",
        "patient076_ED",
        "patient076_ES",
        "patient082_ED",
        "patient082_ES",
        "patient087_ED",
        "patient087_ES",
        "patient089_ED",
        "patient089_ES",
        "patient095_ED",
        "patient095_ES",
        "patient098_ED",
        "patient098_ES"
      ]
    }
  }
}
